<?xml version="1.0" encoding="UTF-8"?>
<XmlLibrary xmlns="http://www.iflow.pt/Library" xmlns:xsi="http://www.w3.org/2001/XMLSchema-instance"
		xsi:schemaLocation="http://www.iflow.pt/Library ../schemas/xmllibrary.xsd">
  <name>Administration</name>
  <version>1.0</version>
  <author>iKnow</author>
  <description>Administration</description>
  <i18nName>library.administration.name</i18nName>
  <i18nDescription>library.administration.description</i18nDescription>
  <XmlBlock>
    <class>BlockAdminOperationsTerminateProcess</class>
    <XmlPort>
      <name>portIn</name>
      <description>portIn</description>
      <in_out>in</in_out>
      <position>
        <x>-5</x>
        <y>25</y>
      </position>
    </XmlPort>
    <XmlPort>
       <name>portTrue</name>
       <description>portTrue</description>
       <in_out>out</in_out>
       <position>
           <x>105</x>
           <y>10</y>
       </position>
    </XmlPort>
    <XmlPort>
        <name>portFalse</name>
        <description>portFalse</description>
        <in_out>out</in_out>
        <position>
            <x>105</x>
            <y>40</y>
        </position>
    </XmlPort>
    <className>pt.iknow.floweditor.blocks.AlteraAtributosAdminOperationsTerminateProcess</className>
    <image>bpmn_task.png</image>
    <description><i18n>library.administration.block.terminate_process.desc</i18n></description>
    <color r="0" g="0" b="255" a="127"/>
    <i18n>library.administration.block.terminate_process.name</i18n>
  </XmlBlock>
  <XmlBlock>
    <class>BlockAdminOperationsRedirectProcessToUser</class>
    <XmlPort>
      <name>portIn</name>
      <description>portIn</description>
      <in_out>in</in_out>
      <position>
        <x>-5</x>
        <y>25</y>
      </position>
    </XmlPort>
    <XmlPort>
       <name>portTrue</name>
       <description>portTrue</description>
       <in_out>out</in_out>
       <position>
           <x>105</x>
           <y>10</y>
       </position>
    </XmlPort>
    <XmlPort>
        <name>portFalse</name>
        <description>portFalse</description>
        <in_out>out</in_out>
        <position>
            <x>105</x>
            <y>40</y>
        </position>
    </XmlPort>
    <className>pt.iknow.floweditor.blocks.AlteraAtributosAdminOperationsRedirectProcessToUser</className>
    <image>bpmn_task.png</image>
    <description><i18n>library.administration.block.redirect_process_to_user.desc</i18n></description>
    <color r="0" g="0" b="255" a="127"/>
    <i18n>library.administration.block.redirect_process_to_user.name</i18n>
  </XmlBlock>
  <XmlBlock>
    <class>BlockAdminOperationsUndoProcess</class>
    <XmlPort>
      <name>portIn</name>
      <description>portIn</description>
      <in_out>in</in_out>
      <position>
        <x>-5</x>
        <y>25</y>
      </position>
    </XmlPort>
    <XmlPort>
       <name>portTrue</name>
       <description>portTrue</description>
       <in_out>out</in_out>
       <position>
           <x>105</x>
           <y>10</y>
       </position>
    </XmlPort>
    <XmlPort>
        <name>portFalse</name>
        <description>portFalse</description>
        <in_out>out</in_out>
        <position>
            <x>105</x>
            <y>40</y>
        </position>
    </XmlPort>
    <className>pt.iknow.floweditor.blocks.AlteraAtributosAdminOperationsUndoProcess</className>
    <image>bpmn_task.png</image>
    <description><i18n>library.administration.block.undo_process.desc</i18n></description>
    <color r="0" g="0" b="255" a="127"/>
    <i18n>library.administration.block.undo_process.name</i18n>
  </XmlBlock>
  <XmlBlock>
    <class>BlockAdminMigrateDocument</class>
    <XmlAttribute>
        <name>docid</name>
        <description>docid</description>
        <value />
    </XmlAttribute>
      <XmlPort>
      <name>portIn</name>
      <description>portIn</description>
      <in_out>in</in_out>
      <position>
        <x>-2</x>
        <y>40</y>
      </position>
    </XmlPort>
    <XmlPort>
      <name>portSuccess</name>
      <description>portSuccess</description>
      <in_out>out</in_out>
      <position>
        <x>105</x>
        <y>20</y>
      </position>
    </XmlPort>
    <XmlPort>
      <name>portEmpty</name>
      <description>portEmpty</description>
      <in_out>out</in_out>
      <position>
        <x>105</x>
        <y>39</y>
      </position>
    </XmlPort>
    <XmlPort>
      <name>portError</name>
      <description>portError</description>
      <in_out>out</in_out>
      <position>
        <x>105</x>
        <y>62</y>
      </position>
    </XmlPort>
    <image>bpmn_task.png</image>
    <description><i18n>library.administration.block.migrate_document</i18n></description>    
    <i18n>library.administration.block.migrate_document</i18n>
  </XmlBlock>
</XmlLibrary>